gemcaplib/__init__.py
gemcaplib/config.py
gemcaplib/database.py
gemcaplib/form.py
gemcaplib/gemini.py
gemcaplib/page.py
gemcaplib/ui.py
gemcaplib-0.2.2.dist-info/METADATA
gemcaplib-0.2.2.dist-info/WHEEL
gemcaplib-0.2.2.dist-info/licenses/LICENSE
gemcaplib-0.2.2.dist-info/RECORD
