Metadata-Version: 2.4
Name: gemcaplib
Version: 0.2.2
Summary: Gemtext renderer with state persistence.
Project-URL: Homepage, https://git.sr.ht/~abraxas/gemini-capsule-library
Project-URL: Bug Tracker, https://todo.sr.ht/~abraxas/GCL-Improvements
Author-email: abraxas <abraxas@hidden.nexus>
Maintainer-email: abraxas <abraxas@hidden.nexus>
License-Expression: GPL-3.0-or-later
License-File: LICENSE
Keywords: cgi,gcl,gemcaplib,gemini,gemtext,gmi,hypertext
Classifier: Programming Language :: Python
Requires-Python: >=3.8
Requires-Dist: tinydb
